iLibrary7/__init__.py
iLibrary7/piewithrise1.py
florestdevinstruments-13.0.0.dist-info/METADATA
florestdevinstruments-13.0.0.dist-info/WHEEL
florestdevinstruments-13.0.0.dist-info/top_level.txt
florestdevinstruments-13.0.0.dist-info/RECORD
